pyrastreio/__init__.py
pyrastreio/cli.py
pyrastreio-0.2.0.dist-info/LICENSE
pyrastreio-0.2.0.dist-info/METADATA
pyrastreio-0.2.0.dist-info/WHEEL
pyrastreio-0.2.0.dist-info/entry_points.txt
pyrastreio-0.2.0.dist-info/top_level.txt
pyrastreio-0.2.0.dist-info/RECORD
