Metadata-Version: 2.1
Name: pyrastreio
Version: 0.2.0
Summary: Biblioteca/CLI para rastreio de encomendas de diversos sistemas.
Home-page: https://github.com/pyanderson/pyrastreio
Author: Anderson Lima
Author-email: anderson.sl93@hotmail.com
License: MIT License
Keywords: rastreio encomenda correios jadlog sequoia
Platform: UNKNOWN
Classifier: Environment :: Console
Classifier: Programming Language :: Python :: 3
Classifier: License :: OSI Approved :: MIT License
Classifier: Operating System :: OS Independent
Classifier: Natural Language :: Portuguese (Brazilian)
Requires-Dist: beautifulsoup4
Requires-Dist: requests
Requires-Dist: click
Requires-Dist: tabulate
